flask_headless_payments/__init__.py
flask_headless_payments/__version__.py
flask_headless_payments/config.py
flask_headless_payments/core.py
flask_headless_payments/decorators.py
flask_headless_payments/errors.py
flask_headless_payments/extensions.py
flask_headless_payments/models.py
flask_headless_payments/extensibility/__init__.py
flask_headless_payments/extensibility/events.py
flask_headless_payments/extensibility/hooks.py
flask_headless_payments/extensibility/plugins.py
flask_headless_payments/managers/__init__.py
flask_headless_payments/managers/checkout_manager.py
flask_headless_payments/managers/plan_manager.py
flask_headless_payments/managers/subscription_manager.py
flask_headless_payments/managers/subscription_manager_old_backup.py
flask_headless_payments/managers/subscription_manager_prod.py
flask_headless_payments/managers/subscription_manager_unified.py
flask_headless_payments/managers/webhook_manager.py
flask_headless_payments/migrations/__init__.py
flask_headless_payments/mixins/__init__.py
flask_headless_payments/mixins/customer.py
flask_headless_payments/mixins/payment.py
flask_headless_payments/mixins/subscription.py
flask_headless_payments/mixins/webhook.py
flask_headless_payments/routes/__init__.py
flask_headless_payments/routes/health.py
flask_headless_payments/routes/payments.py
flask_headless_payments/utils/__init__.py
flask_headless_payments/utils/idempotency.py
flask_headless_payments/utils/monitoring.py
flask_headless_payments/utils/retry.py
flask_headless_payments/utils/security.py
flask_headless_payments/utils/validation.py
flask_headless_payments-0.2.10.dist-info/licenses/LICENSE
flask_headless_payments-0.2.10.dist-info/METADATA
flask_headless_payments-0.2.10.dist-info/WHEEL
flask_headless_payments-0.2.10.dist-info/top_level.txt
flask_headless_payments-0.2.10.dist-info/RECORD
