Metadata-Version: 2.4
Name: flask-headless-payments
Version: 0.2.10
Summary: Modern, headless payment integration for Flask APIs. Stripe subscriptions + webhooks + plan management in one line.
Author-email: Dhruv Agnihotri <dagni@umich.edu>
License-Expression: MIT
Project-URL: Homepage, https://github.com/Dhruvagnihotri/flask-headless-payments
Project-URL: Repository, https://github.com/Dhruvagnihotri/flask-headless-payments
Project-URL: Issues, https://github.com/Dhruvagnihotri/flask-headless-payments/issues
Project-URL: Documentation, https://github.com/Dhruvagnihotri/flask-headless-payments#readme
Keywords: flask,payments,stripe,subscription,saas,headless,api,billing,checkout,webhooks
Classifier: Development Status :: 3 - Alpha
Classifier: Intended Audience :: Developers
Classifier: Programming Language :: Python :: 3
Classifier: Programming Language :: Python :: 3.8
Classifier: Programming Language :: Python :: 3.9
Classifier: Programming Language :: Python :: 3.10
Classifier: Programming Language :: Python :: 3.11
Classifier: Programming Language :: Python :: 3.12
Classifier: Framework :: Flask
Classifier: Topic :: Software Development :: Libraries :: Python Modules
Classifier: Topic :: Office/Business :: Financial
Requires-Python: >=3.8
License-File: LICENSE
Requires-Dist: Flask>=2.0.0
Requires-Dist: Flask-SQLAlchemy>=3.0.0
Requires-Dist: Flask-JWT-Extended>=4.5.0
Requires-Dist: Flask-CORS>=4.0.0
Requires-Dist: stripe>=5.0.0
Requires-Dist: python-dotenv>=1.0.0
Requires-Dist: Werkzeug>=2.0.0
Requires-Dist: marshmallow>=3.19.0
Requires-Dist: Flask-Migrate>=4.0.0
Requires-Dist: redis>=4.0.0
Requires-Dist: tenacity>=8.2.0
Provides-Extra: dev
Requires-Dist: pytest>=7.4.0; extra == "dev"
Requires-Dist: pytest-cov>=4.1.0; extra == "dev"
Requires-Dist: black>=23.7.0; extra == "dev"
Requires-Dist: flake8>=6.1.0; extra == "dev"
Dynamic: license-file
